vidpkg/__init__.py
vidpkg/player.py
vidpkg-0.0.1.dist-info/LICENSE
vidpkg-0.0.1.dist-info/METADATA
vidpkg-0.0.1.dist-info/WHEEL
vidpkg-0.0.1.dist-info/top_level.txt
vidpkg-0.0.1.dist-info/RECORD
