Metadata-Version: 2.1
Name: vidpkg
Version: 0.0.1
Summary: A small video player package
Home-page: https://github.com/dhruvak99
Author: Captain Jack Sparrow
Author-email: sparrow@yahoo.com
License: UNKNOWN
Project-URL: Bug Tracker, https://github.com/pypa/dhruvak99
Platform: UNKNOWN
Classifier: Programming Language :: Python :: 3
Classifier: License :: OSI Approved :: MIT License
Classifier: Operating System :: OS Independent
Requires-Python: >=3.6
License-File: LICENSE
Requires-Dist: tk
Requires-Dist: python-vlc
Requires-Dist: Pillow
